[
  {
    "featureType": "landscape",
    "elementType": "geometry.fill",
    "stylers": [
      {
        "color": "#dde3ed"
      }
    ]
  },
  {
    "featureType": "poi",
    "elementType": "geometry.fill",
    "stylers": [
      {
        "color": "#bbc9db"
      }
    ]
  },
  {
    "featureType": "road",
    "elementType": "geometry.fill",
    "stylers": [
      {
        "color": "#748eb6"
      },
      {
        "visibility": "on"
      }
    ]
  },
  {
    "featureType": "road",
    "elementType": "geometry.stroke",
    "stylers": [
      {
        "color": "#bbc9db"
      }
    ]
  },
  {
    "featureType": "water",
    "stylers": [
      {
        "color": "#eaeef4"
      }
    ]
  }
]